LICENSE
MANIFEST.in
README.md
setup.py
pyasmer/__init__.py
pyasmer/asm_helper.py
pyasmer/asm_instruction.py
pyasmer/code_view.py
pyasmer/code_writer.py
pyasmer/op_help.py
pyasmer/structure.py
pyasmer.egg-info/PKG-INFO
pyasmer.egg-info/SOURCES.txt
pyasmer.egg-info/dependency_links.txt
pyasmer.egg-info/top_level.txt
src/pyasmer.c
src/clinic/v3_10.h
src/clinic/v3_6.h
src/clinic/v3_7.h
src/clinic/v3_8.h
src/clinic/v3_9.h