Metadata-Version: 2.1
Name: pyasmer
Version: 0.1.1
Summary: pyasmer
Home-page: https://github.com/penguin-wwy/pyasmer
Author: penguin-wwy
Author-email: penguin.wenyang.wang@gmail.com
License: MIT License
Platform: UNKNOWN
Classifier: Intended Audience :: Developers
Classifier: License :: OSI Approved :: MIT License
Classifier: Operating System :: POSIX :: Linux
Classifier: Programming Language :: Python :: 3.6
Classifier: Programming Language :: Python :: 3.7
Classifier: Programming Language :: Python :: 3.8
Classifier: Programming Language :: Python :: 3.9
Classifier: Programming Language :: Python :: 3.10
Classifier: Programming Language :: Python :: Implementation :: CPython
Requires-Python: >=3.6,<3.11
License-File: LICENSE
